MANIFEST.in
VERSION
requirements.txt
setup.py
ddd/__init__.py
ddd/aggregatemeta.py
ddd/aggregateroot.py
ddd/aggregaterootmetaclass.py
ddd/aggregatestate.py
ddd/aggregatestatedescriptor.py
ddd/entity.py
ddd/exc.py
ddd/factory.py
ddd/factorymetaclass.py
ddd/filterresult.py
ddd/memoryrepository.py
ddd/package.json
ddd/predicate.py
ddd/predicateoperator.py
ddd/repository.py
ddd/repositorymetaclass.py
ddd/utils.py
ddd.egg-info/PKG-INFO
ddd.egg-info/SOURCES.txt
ddd.egg-info/dependency_links.txt
ddd.egg-info/requires.txt
ddd.egg-info/top_level.txt
ddd/ext/__init__.py
ddd/ext/google/__init__.py
ddd/ext/google/datastorecursor.py
ddd/ext/google/datastoreobjectrepository.py
ddd/ext/google/datastorequery.py
ddd/ext/google/runner.py
ddd/test/__init__.py
ddd/test/fulfillment.py
ddd/test/fulfillmentfactory.py
ddd/test/fulfillmentitem.py
ddd/test/fulfillmentrepository.py
ddd/test/fulfillmentstatus.py
ddd/test/repository.py
ddd/types/__init__.py
ddd/types/icursor.py
ddd/types/irepository.py
docs/source/conf.py
tests/test_unit_concurrent.py
tests/test_unit_fulfillment.py
tests/test_unit_predicate.py
tests/ext/__init__.py
tests/ext/google/conftest.py
tests/ext/google/test_integration_datastoreobjectrepository.py